ibet/__init__.py
ibet/client.py
ibet/exceptions.py
ibet/settings.py
cc_ibet-2.1.5.dist-info/METADATA
cc_ibet-2.1.5.dist-info/WHEEL
cc_ibet-2.1.5.dist-info/top_level.txt
cc_ibet-2.1.5.dist-info/RECORD
