Metadata-Version: 2.1
Name: cc-ibet
Version: 2.1.5
Author: namlehong
Author-email: namlehong@gmail.com
License: MIT
Requires-Python: >=3.7
Requires-Dist: requests
Requires-Dist: cc-api-helper
Requires-Dist: beautifulsoup4
Requires-Dist: pycryptodome
